[
  {
    "Name": "prop_dart_bd_cab_01",
    "Position": {
      "X": -132.12634,
      "Y": 870.5353,
      "Z": 233.73894
    },
    "Rotation": {
      "X": 0.0,
      "Y": -0.0,
      "Z": -33.216114
    }
  },
  {
    "Name": "prop_dart_bd_01",
    "Position": {
      "X": 3310.6267,
      "Y": 5175.3916,
      "Z": 20.474304
    },
    "Rotation": {
      "X": 0.0,
      "Y": 0.0,
      "Z": 142.40543
    }
  },
  {
    "Name": "prop_dart_bd_cab_01",
    "Position": {
      "X": 974.2843,
      "Y": 2723.242,
      "Z": 40.2436
    },
    "Rotation": {
      "X": 0.0,
      "Y": -0.0,
      "Z": -90.00001
    }
  },
  {
    "Name": "prop_dart_bd_01",
    "Position": {
      "X": -32.158768,
      "Y": 2869.9622,
      "Z": 59.12062
    },
    "Rotation": {
      "X": -4.981039,
      "Y": -0.43518776,
      "Z": -110.335724
    }
  },
  {
    "Name": "prop_dart_bd_cab_01",
    "Position": {
      "X": 5025.5986,
      "Y": -5760.192,
      "Z": 16.36293
    },
    "Rotation": {
      "X": -0.0,
      "Y": 0.0,
      "Z": 48.708252
    }
  },
  {
    "Name": "prop_dart_bd_01",
    "Position": {
      "X": 576.40906,
      "Y": -3123.5347,
      "Z": 19.37094
    },
    "Rotation": {
      "X": 0.0,
      "Y": -0.0,
      "Z": -90.00001
    }
  },
  {
    "Name": "prop_dart_bd_cab_01",
    "Position": {
      "X": -572.04065,
      "Y": 294.19574,
      "Z": 79.9374
    },
    "Rotation": {
      "X": 0.0,
      "Y": -0.0,
      "Z": -4.999957
    }
  },
  {
    "Name": "prop_dart_bd_cab_01",
    "Position": {
      "X": 1992.2932,
      "Y": 3050.5828,
      "Z": 47.989727
    },
    "Rotation": {
      "X": -8.65703E-05,
      "Y": -0.00086839846,
      "Z": 57.78316
    }
  },
  {
    "Name": "prop_dart_bd_cab_01",
    "Position": {
      "X": 989.1318,
      "Y": -100.394646,
      "Z": 75.57692
    },
    "Rotation": {
      "X": 0.0,
      "Y": -0.0,
      "Z": -137.34814
    }
  },
  {
    "Name": "prop_dart_bd_cab_01",
    "Position": {
      "X": 1119.8805,
      "Y": -3157.0261,
      "Z": -36.339706
    },
    "Rotation": {
      "X": 0.0,
      "Y": -0.0,
      "Z": -89.99995
    }
  },
  {
    "Name": "prop_dart_bd_cab_01",
    "Position": {
      "X": 1000.935,
      "Y": -3162.8154,
      "Z": -33.48268
    },
    "Rotation": {
      "X": 0.0,
      "Y": -0.0,
      "Z": 0.0
    }
  },
  {
    "Name": "prop_dart_bd_cab_01",
    "Position": {
      "X": 512.37836,
      "Y": 4825.67,
      "Z": -65.67694
    },
    "Rotation": {
      "X": 0.0,
      "Y": -0.0,
      "Z": 0.0
    }
  },
  {
    "Name": "prop_dart_bd_cab_01",
    "Position": {
      "X": 556.5492,
      "Y": -421.07712,
      "Z": -68.93912
    },
    "Rotation": {
      "X": 0.0,
      "Y": -0.0,
      "Z": -179.99988
    }
  }
]